eea_frame-0.5.8.dist-info/licenses/LICENSE
frame/__init__.py
frame/admin.py
frame/apps.py
frame/backends.py
frame/loaders.py
frame/middleware.py
frame/models.py
frame/tests.py
frame/utils.py
frame/views.py
frame/migrations/0001_initial.py
frame/migrations/__init__.py
frame/templates/frame.html
eea_frame-0.5.8.dist-info/METADATA
eea_frame-0.5.8.dist-info/WHEEL
eea_frame-0.5.8.dist-info/top_level.txt
eea_frame-0.5.8.dist-info/RECORD
