Metadata-Version: 2.4
Name: eea.frame
Version: 0.5.8
Summary: Django integration middleware for EEA Zope websites
Home-page: https://github.com/eea/eea.frame
Author: Diana Boiangiu
Author-email: diana.boiangiu@eaudeweb.ro
License-File: LICENSE
Requires-Dist: Django>=2.2
Requires-Dist: requests>=2.25.1
Dynamic: author
Dynamic: author-email
Dynamic: description
Dynamic: home-page
Dynamic: license-file
Dynamic: requires-dist
Dynamic: summary
